stalker_pyramid
tests
