Metadata-Version: 1.1
Name: stalker-pyramid
Version: 0.3.1
Summary: Stalker (ProdAM) Based Web App
Home-page: https://github.com/eoyilmaz/stalker_pyramid/
Author: Erkan Ozgur Yilmaz
Author-email: eoyilmaz@gmail.com
License: MIT
Keywords: web,wsgi,bfg,pylons,pyramid,production,asset,management,vfx,animation,houdini,nuke,fusion,xsi,blender,vue
Platform: UNKNOWN
Classifier: Programming Language :: Python
Classifier: Framework :: Pyramid
Classifier: License :: OSI Approved :: MIT License
Classifier: Operating System :: OS Independent
Classifier: Development Status :: 4 - Beta
Classifier: Intended Audience :: Developers
Classifier: Intended Audience :: End Users/Desktop
Classifier: Topic :: Internet :: WWW/HTTP
Classifier: Topic :: Internet :: WWW/HTTP :: WSGI :: Application
Classifier: Topic :: Database
Classifier: Topic :: Software Development
Classifier: Topic :: Utilities
Classifier: Topic :: Office/Business :: Scheduling
